<annotation>
	<folder>Nuova cartella (2)</folder>
	<filename>b.fbc18e4a-b95d-11ee-b491-8070f4b30e00.jpg</filename>
	<path>C:\Users\crist\Desktop\Nuova cartella (2)\b.fbc18e4a-b95d-11ee-b491-8070f4b30e00.jpg</path>
	<source>
		<database>Unknown</database>
	</source>
	<size>
		<width>1920</width>
		<height>1080</height>
		<depth>3</depth>
	</size>
	<segmented>0</segmented>
	<object>
		<name>b</name>
		<pose>Unspecified</pose>
		<truncated>0</truncated>
		<difficult>0</difficult>
		<bndbox>
			<xmin>73</xmin>
			<ymin>153</ymin>
			<xmax>480</xmax>
			<ymax>853</ymax>
		</bndbox>
	</object>
</annotation>
