<annotation>
	<folder>Nuova cartella</folder>
	<filename>20240206_215301(0).jpg</filename>
	<path>C:\Users\Iacopo\Desktop\Nuova cartella\20240206_215301(0).jpg</path>
	<source>
		<database>Unknown</database>
	</source>
	<size>
		<width>1024</width>
		<height>768</height>
		<depth>3</depth>
	</size>
	<segmented>0</segmented>
	<object>
		<name>space</name>
		<pose>Unspecified</pose>
		<truncated>0</truncated>
		<difficult>0</difficult>
		<bndbox>
			<xmin>10</xmin>
			<ymin>317</ymin>
			<xmax>997</xmax>
			<ymax>525</ymax>
		</bndbox>
	</object>
</annotation>
